ple/__init__.py
ple/_modidx.py
ple/all.py
ple/base_exp.py
ple/datasets.py
ple/lit_model.py
ple/loss.py
ple/persistance.py
ple/trainer.py
fast_ple-0.0.4.dist-info/LICENSE
fast_ple-0.0.4.dist-info/METADATA
fast_ple-0.0.4.dist-info/WHEEL
fast_ple-0.0.4.dist-info/entry_points.txt
fast_ple-0.0.4.dist-info/top_level.txt
fast_ple-0.0.4.dist-info/RECORD
